DjvuRleImagePlugin.py
DjvuRleImagePlugin-0.1.0.dist-info/LICENSE
DjvuRleImagePlugin-0.1.0.dist-info/METADATA
DjvuRleImagePlugin-0.1.0.dist-info/WHEEL
DjvuRleImagePlugin-0.1.0.dist-info/top_level.txt
DjvuRleImagePlugin-0.1.0.dist-info/RECORD
