Metadata-Version: 2.1
Name: DjvuRleImagePlugin
Version: 0.1.0
Summary: Pillow plugin for the DjVu RLE image file format
Home-page: https://github.com/Piolie/DjvuRleImagePlugin
Author: Piolie
License: Historical Permission Notice and Disclaimer (HPND) License
Keywords: image,pillow,plugin,DjVu,RLE,djvurle,codec,encoder,decoder
Platform: UNKNOWN
Classifier: Programming Language :: Python :: 3
Classifier: Programming Language :: Python :: 3 :: Only
Classifier: License :: OSI Approved :: Historical Permission Notice and Disclaimer (HPND)
Classifier: Operating System :: OS Independent
Classifier: Topic :: Multimedia :: Graphics
Classifier: Topic :: Multimedia :: Graphics :: Viewers
Classifier: Topic :: Multimedia :: Graphics :: Graphics Conversion
Requires-Python: >=3.6
License-File: LICENSE
Requires-Dist: pillow (>=8.0.0)
